cortex_mcp/ACCOUNTABILITY_AUDIT.md
cortex_mcp/API_REFERENCE.md
cortex_mcp/AUTOMATION_DESIGN.md
cortex_mcp/AUTOMATION_IMPOSSIBLE_TOOLS.md
cortex_mcp/AUTOMATION_IMPOSSIBLE_TOOLS_SIMPLIFIED.md
cortex_mcp/BENCHMARK_IMPLEMENTATION_FIXES.md
cortex_mcp/BETA_RECRUITMENT.md
cortex_mcp/BETA_TEST_GUIDE.md
cortex_mcp/CLAUDE.md
cortex_mcp/CLAUDE_DESKTOP_SETUP.md
cortex_mcp/COMPREHENSIVE_VERIFICATION_REPORT.md
cortex_mcp/CORTEX_AUTOMATION_TEST_REPORT.md
cortex_mcp/FEATURE_VERIFICATION_REPORT.md
cortex_mcp/FEEDBACK_COLLECTION_SYSTEM.md
cortex_mcp/FINAL_PHASE_REPORT.md
cortex_mcp/GOAL_FEATURE_MAPPING.md
cortex_mcp/INSTALLATION.md
cortex_mcp/LOG_SYSTEM_REVIEW.md
cortex_mcp/MANUAL_TEST_GUIDE.md
cortex_mcp/MEMORY_BLOAT_FIX_REPORT.md
cortex_mcp/PERFORMANCE_TRADEOFF_ANALYSIS.md
cortex_mcp/PHASE9_COMPLETE_AUDIT.md
cortex_mcp/PHASE9_DIAGNOSIS.md
cortex_mcp/QA_TEST_PLAN.md
cortex_mcp/README.md
cortex_mcp/SKIP_TESTS.md
cortex_mcp/SYSTEM_PROMPT_MIGRATION_GUIDE.md
cortex_mcp/TELEMETRY_EVENTS_MAPPING.md
cortex_mcp/TELEMETRY_MASTER_PLAN.md
cortex_mcp/TELEMETRY_MIGRATION_v2.md
cortex_mcp/TELEMETRY_V2_FINAL_REPORT.md
cortex_mcp/ULTRATHINK_BLIND_SPOT_ANALYSIS.md
cortex_mcp/ULTRATHINK_VERIFICATION.md
cortex_mcp/VERSION_PINNING.md
cortex_mcp/__init__.py
cortex_mcp/__main__.py
cortex_mcp/answer.md
cortex_mcp/bench_test.md
cortex_mcp/cleanup_merged_files.py
cortex_mcp/cli.py
cortex_mcp/config.py
cortex_mcp/cortex_prompt.md
cortex_mcp/cortex_protocols.md
cortex_mcp/debug_rag_metadata.py
cortex_mcp/debug_roc_auc.py
cortex_mcp/debug_snapshot_restore.py
cortex_mcp/final_report.md
cortex_mcp/final_test.md
cortex_mcp/fix_memory_bloat.py
cortex_mcp/hal.md
cortex_mcp/main 2.py
cortex_mcp/main 3.py
cortex_mcp/main.py
cortex_mcp/performance_optimization.md
cortex_mcp/pytest_collect_output.txt
cortex_mcp/requirements.txt
cortex_mcp/run_final_tests.py
cortex_mcp/run_final_tests_v2.py
cortex_mcp/run_first_20_tests.py
cortex_mcp/setup_test_user.py
cortex_mcp/test_analysis.md
cortex_mcp/test_api_integration.py
cortex_mcp-1.0.5.dist-info/licenses/LICENSE
cortex_mcp-1.0.5.dist-info/METADATA
cortex_mcp-1.0.5.dist-info/WHEEL
cortex_mcp-1.0.5.dist-info/entry_points.txt
cortex_mcp-1.0.5.dist-info/top_level.txt
cortex_mcp-1.0.5.dist-info/RECORD
