Metadata-Version: 2.4
Name: cortex-mcp
Version: 1.0.5
Summary: Making AI Accountable Over Time - MCP server for persistent memory, automatic verification, and evidence-based grounding
Author-email: Cortex Team <beta@cortex-mcp.com>
Maintainer-email: Cortex Team <beta@cortex-mcp.com>
License: MIT
Project-URL: Homepage, https://github.com/syab726/cortex
Project-URL: Documentation, https://github.com/syab726/cortex#readme
Project-URL: Repository, https://github.com/syab726/cortex
Project-URL: Issues, https://github.com/syab726/cortex/issues
Project-URL: Changelog, https://github.com/syab726/cortex/releases
Keywords: mcp,model-context-protocol,ai-memory,accountability,hallucination-detection,rag,vector-database,claude,anthropic
Classifier: Development Status :: 4 - Beta
Classifier: Intended Audience :: Developers
Classifier: Programming Language :: Python :: 3
Classifier: Programming Language :: Python :: 3.11
Classifier: Programming Language :: Python :: 3.12
Classifier: Topic :: Scientific/Engineering :: Artificial Intelligence
Classifier: Topic :: Software Development :: Libraries :: Python Modules
Classifier: Operating System :: OS Independent
Requires-Python: >=3.11
License-File: LICENSE
Requires-Dist: mcp<2.0.0,>=1.0.0
Requires-Dist: chromadb<2.0.0,>=1.0.0
Requires-Dist: numpy==1.26.4
Requires-Dist: torch==2.1.2
Requires-Dist: transformers==4.36.2
Requires-Dist: sentence-transformers==2.5.1
Requires-Dist: google-auth>=2.0.0
Requires-Dist: google-auth-oauthlib>=1.0.0
Requires-Dist: google-api-python-client>=2.0.0
Requires-Dist: cryptography>=41.0.0
Requires-Dist: pyyaml>=6.0.0
Requires-Dist: aiohttp>=3.9.0
Requires-Dist: python-dateutil>=2.8.0
Requires-Dist: portalocker>=2.8.0
Requires-Dist: GitPython>=3.1.0
Requires-Dist: networkx>=3.0
Requires-Dist: requests>=2.31.0
Provides-Extra: dev
Requires-Dist: pytest>=7.4.0; extra == "dev"
Requires-Dist: pytest-asyncio>=0.21.0; extra == "dev"
Requires-Dist: pytest-cov>=4.1.0; extra == "dev"
Requires-Dist: black>=23.7.0; extra == "dev"
Requires-Dist: isort>=5.12.0; extra == "dev"
Requires-Dist: flake8>=6.1.0; extra == "dev"
Requires-Dist: mypy>=1.5.0; extra == "dev"
Dynamic: license-file
